{
  "Confirmation JSR223 Sampler" : {
    "transaction" : "Confirmation JSR223 Sampler",
    "sampleCount" : 100,
    "errorCount" : 0,
    "errorPct" : 0.0,
    "meanResTime" : 1.5300000000000005,
    "medianResTime" : 1.0,
    "minResTime" : 0.0,
    "maxResTime" : 20.0,
    "pct1ResTime" : 2.0,
    "pct2ResTime" : 2.9499999999999886,
    "pct3ResTime" : 19.829999999999913,
    "throughput" : 0.3392786257858541,
    "receivedKBytesPerSec" : 0.0,
    "sentKBytesPerSec" : 0.0
  },
  "Reserve logging JSR223 Sampler" : {
    "transaction" : "Reserve logging JSR223 Sampler",
    "sampleCount" : 100,
    "errorCount" : 0,
    "errorPct" : 0.0,
    "meanResTime" : 1.5899999999999996,
    "medianResTime" : 1.0,
    "minResTime" : 0.0,
    "maxResTime" : 23.0,
    "pct1ResTime" : 2.0,
    "pct2ResTime" : 3.0,
    "pct3ResTime" : 22.829999999999913,
    "throughput" : 0.33919231525890553,
    "receivedKBytesPerSec" : 0.0,
    "sentKBytesPerSec" : 0.0
  },
  "Travel the world_4-225" : {
    "transaction" : "Travel the world_4-225",
    "sampleCount" : 100,
    "errorCount" : 0,
    "errorPct" : 0.0,
    "meanResTime" : 441.90999999999997,
    "medianResTime" : 438.5,
    "minResTime" : 397.0,
    "maxResTime" : 567.0,
    "pct1ResTime" : 469.8,
    "pct2ResTime" : 484.9,
    "pct3ResTime" : 566.97,
    "throughput" : 0.33877978297767103,
    "receivedKBytesPerSec" : 0.7859293957523791,
    "sentKBytesPerSec" : 0.2734124885238348
  },
  "Get To and From Port JSR223 Sampler" : {
    "transaction" : "Get To and From Port JSR223 Sampler",
    "sampleCount" : 100,
    "errorCount" : 0,
    "errorPct" : 0.0,
    "meanResTime" : 13.78,
    "medianResTime" : 2.0,
    "minResTime" : 0.0,
    "maxResTime" : 1200.0,
    "pct1ResTime" : 3.0,
    "pct2ResTime" : 3.0,
    "pct3ResTime" : 1188.0499999999938,
    "throughput" : 0.33672754700716556,
    "receivedKBytesPerSec" : 0.0,
    "sentKBytesPerSec" : 0.0
  },
  "Purchase JSR223 Sampler" : {
    "transaction" : "Purchase JSR223 Sampler",
    "sampleCount" : 100,
    "errorCount" : 0,
    "errorPct" : 0.0,
    "meanResTime" : 1.4700000000000002,
    "medianResTime" : 1.0,
    "minResTime" : 0.0,
    "maxResTime" : 17.0,
    "pct1ResTime" : 2.0,
    "pct2ResTime" : 2.0,
    "pct3ResTime" : 16.85999999999993,
    "throughput" : 0.33924179458909337,
    "receivedKBytesPerSec" : 0.0,
    "sentKBytesPerSec" : 0.0
  },
  "Get Confirmation Page Data JSR223 Sampler" : {
    "transaction" : "Get Confirmation Page Data JSR223 Sampler",
    "sampleCount" : 100,
    "errorCount" : 0,
    "errorPct" : 0.0,
    "meanResTime" : 4.200000000000004,
    "medianResTime" : 2.0,
    "minResTime" : 0.0,
    "maxResTime" : 225.0,
    "pct1ResTime" : 3.0,
    "pct2ResTime" : 4.0,
    "pct3ResTime" : 222.81999999999888,
    "throughput" : 0.3381211285130785,
    "receivedKBytesPerSec" : 0.0,
    "sentKBytesPerSec" : 0.0
  },
  "Travel the world_2-182" : {
    "transaction" : "Travel the world_2-182",
    "sampleCount" : 100,
    "errorCount" : 0,
    "errorPct" : 0.0,
    "meanResTime" : 606.5799999999998,
    "medianResTime" : 596.5,
    "minResTime" : 548.0,
    "maxResTime" : 1120.0,
    "pct1ResTime" : 650.9,
    "pct2ResTime" : 704.0499999999997,
    "pct3ResTime" : 1116.4799999999982,
    "throughput" : 0.3379051905616322,
    "receivedKBytesPerSec" : 0.7816862408807838,
    "sentKBytesPerSec" : 0.2115999261677159
  },
  "Total" : {
    "transaction" : "Total",
    "sampleCount" : 1000,
    "errorCount" : 0,
    "errorPct" : 0.0,
    "meanResTime" : 196.7540000000002,
    "medianResTime" : 2.0,
    "minResTime" : 0.0,
    "maxResTime" : 1200.0,
    "pct1ResTime" : 558.8,
    "pct2ResTime" : 601.9499999999999,
    "pct3ResTime" : 661.99,
    "throughput" : 3.262898236729793,
    "receivedKBytesPerSec" : 3.058011169716389,
    "sentKBytesPerSec" : 0.852479960706548
  },
  "Get Purchase Page Data JSR223 Sampler" : {
    "transaction" : "Get Purchase Page Data JSR223 Sampler",
    "sampleCount" : 100,
    "errorCount" : 0,
    "errorPct" : 0.0,
    "meanResTime" : 1.5399999999999998,
    "medianResTime" : 1.0,
    "minResTime" : 0.0,
    "maxResTime" : 25.0,
    "pct1ResTime" : 2.9000000000000057,
    "pct2ResTime" : 3.0,
    "pct3ResTime" : 24.789999999999893,
    "throughput" : 0.3380948356013862,
    "receivedKBytesPerSec" : 0.0,
    "sentKBytesPerSec" : 0.0
  },
  "Travel the world_5" : {
    "transaction" : "Travel the world_5",
    "sampleCount" : 100,
    "errorCount" : 0,
    "errorPct" : 0.0,
    "meanResTime" : 443.49999999999994,
    "medianResTime" : 435.0,
    "minResTime" : 396.0,
    "maxResTime" : 680.0,
    "pct1ResTime" : 471.9,
    "pct2ResTime" : 512.1999999999998,
    "pct3ResTime" : 679.7299999999999,
    "throughput" : 0.33883258620748075,
    "receivedKBytesPerSec" : 0.7571485469588082,
    "sentKBytesPerSec" : 0.1694162931037404
  },
  "Travel the world_4" : {
    "transaction" : "Travel the world_4",
    "sampleCount" : 100,
    "errorCount" : 0,
    "errorPct" : 0.0,
    "meanResTime" : 443.44000000000017,
    "medianResTime" : 440.0,
    "minResTime" : 398.0,
    "maxResTime" : 568.0,
    "pct1ResTime" : 471.8,
    "pct2ResTime" : 486.84999999999997,
    "pct3ResTime" : 567.97,
    "throughput" : 0.33875453507633835,
    "receivedKBytesPerSec" : 0.7858708235800257,
    "sentKBytesPerSec" : 0.2733921121853394
  },
  "Travel the world_5-227" : {
    "transaction" : "Travel the world_5-227",
    "sampleCount" : 100,
    "errorCount" : 0,
    "errorPct" : 0.0,
    "meanResTime" : 443.49999999999994,
    "medianResTime" : 435.0,
    "minResTime" : 396.0,
    "maxResTime" : 680.0,
    "pct1ResTime" : 471.9,
    "pct2ResTime" : 512.1999999999998,
    "pct3ResTime" : 679.7299999999999,
    "throughput" : 0.33883258620748075,
    "receivedKBytesPerSec" : 0.7571485469588082,
    "sentKBytesPerSec" : 0.1694162931037404
  },
  "Travel the world_3" : {
    "transaction" : "Travel the world_3",
    "sampleCount" : 100,
    "errorCount" : 0,
    "errorPct" : 0.0,
    "meanResTime" : 452.90999999999997,
    "medianResTime" : 445.0,
    "minResTime" : 398.0,
    "maxResTime" : 633.0,
    "pct1ResTime" : 502.9,
    "pct2ResTime" : 507.0,
    "pct3ResTime" : 632.93,
    "throughput" : 0.3386994618065552,
    "receivedKBytesPerSec" : 0.8481973885424746,
    "sentKBytesPerSec" : 0.23010725447676011
  },
  "Travel the world_2" : {
    "transaction" : "Travel the world_2",
    "sampleCount" : 100,
    "errorCount" : 0,
    "errorPct" : 0.0,
    "meanResTime" : 608.1700000000002,
    "medianResTime" : 597.5,
    "minResTime" : 550.0,
    "maxResTime" : 1143.0,
    "pct1ResTime" : 652.0,
    "pct2ResTime" : 705.0499999999997,
    "pct3ResTime" : 1139.259999999998,
    "throughput" : 0.33772944494165724,
    "receivedKBytesPerSec" : 0.7812796832519967,
    "sentKBytesPerSec" : 0.2114898723382698
  },
  "Travel the world_3-188" : {
    "transaction" : "Travel the world_3-188",
    "sampleCount" : 100,
    "errorCount" : 0,
    "errorPct" : 0.0,
    "meanResTime" : 451.4399999999999,
    "medianResTime" : 443.5,
    "minResTime" : 397.0,
    "maxResTime" : 632.0,
    "pct1ResTime" : 501.9,
    "pct2ResTime" : 505.95,
    "pct3ResTime" : 631.93,
    "throughput" : 0.3387120811825116,
    "receivedKBytesPerSec" : 0.8482289909597746,
    "sentKBytesPerSec" : 0.23011582788853663
  }
}